{"cameraMode":{"drawMode":0,"name":"Shaded","section":"Shading Mode"},"sceneLighting":true,"audioPlay":false,"sceneViewState":{"m_AlwaysRefresh":false,"showFog":true,"showSkybox":true,"showFlares":true,"showImageEffects":true,"showParticleSystems":true,"showVisualEffectGraphs":true,"m_FxEnabled":false},"in2DMode":false,"pivot":{"x":4.964430332183838,"y":5.08184289932251,"z":9.880698204040528},"rotation":{"x":0.47628650069236758,"y":0.5227759480476379,"z":-0.4786626994609833,"w":0.5203224420547485},"size":5.707395553588867,"orthographic":false}